odoo/addons/geoengine_base_geolocalize/README.rst
odoo/addons/geoengine_base_geolocalize/__init__.py
odoo/addons/geoengine_base_geolocalize/__manifest__.py
odoo/addons/geoengine_base_geolocalize/i18n/geoengine_base_geolocalize.pot
odoo/addons/geoengine_base_geolocalize/i18n/it.po
odoo/addons/geoengine_base_geolocalize/i18n/zh_CN.po
odoo/addons/geoengine_base_geolocalize/models/__init__.py
odoo/addons/geoengine_base_geolocalize/models/res_partner.py
odoo/addons/geoengine_base_geolocalize/readme/CONTRIBUTORS.md
odoo/addons/geoengine_base_geolocalize/readme/DESCRIPTION.md
odoo/addons/geoengine_base_geolocalize/readme/INSTALL.md
odoo/addons/geoengine_base_geolocalize/static/description/icon.png
odoo/addons/geoengine_base_geolocalize/static/description/index.html
odoo/addons/geoengine_base_geolocalize/tests/__init__.py
odoo/addons/geoengine_base_geolocalize/tests/test_geoengine_partner.py
odoo/addons/geoengine_base_geolocalize/views/res_partner_view.xml
odoo_addon_geoengine_base_geolocalize-17.0.1.0.0.3.dist-info/METADATA
odoo_addon_geoengine_base_geolocalize-17.0.1.0.0.3.dist-info/WHEEL
odoo_addon_geoengine_base_geolocalize-17.0.1.0.0.3.dist-info/top_level.txt
odoo_addon_geoengine_base_geolocalize-17.0.1.0.0.3.dist-info/RECORD
